creaocode/__init__.py
creaocode/core/__init__.py
creaocode/core/aflow/__init__.py
creaocode/core/aflow/evaluator.py
creaocode/core/aflow/benchmark/__init__.py
creaocode/core/aflow/benchmark/benchmark.py
creaocode/core/aflow/benchmark/math.py
creaocode/core/aflow/optimizer_utils/__init__.py
creaocode/core/aflow/optimizer_utils/data_utils.py
creaocode/core/aflow/optimizer_utils/evaluation_utils.py
creaocode/core/aflow/optimizer_utils/experience_utils.py
creaocode/core/aflow/optimizer_utils/graph_utils.py
creaocode/core/aflow/prompts/__init__.py
creaocode/core/aflow/prompts/optimze_prompt.py
creaocode/core/aflow/utils/__init__.py
creaocode/core/aflow/utils/common.py
creaocode/core/aflow/workflows/__init__.py
creaocode/core/aflow/workflows/template/__init__.py
creaocode/core/aflow/workflows/template/op_prompt.py
creaocode/core/aflow/workflows/template/operator.py
creaocode/core/aflow/workflows/template/operator_an.py
creaocode/core/aflow/workflows/template/operator_description.py
creaocode-0.2.0.dist-info/METADATA
creaocode-0.2.0.dist-info/WHEEL
creaocode-0.2.0.dist-info/top_level.txt
creaocode-0.2.0.dist-info/RECORD
